runfiles/__init__.py
runfiles/py.typed
runfiles/runfiles.py
bazel_runfiles-1.7.0.dist-info/WHEEL
bazel_runfiles-1.7.0.dist-info/METADATA
bazel_runfiles-1.7.0.dist-info/RECORD
