Metadata-Version: 2.1
Name: bazel_runfiles
Home-page: https://github.com/bazel-contrib/rules_python
Classifier: Development Status :: 5 - Production/Stable
Classifier: License :: OSI Approved :: Apache Software License
Requires-Python: >=3.7
Version: 1.7.0
